QianduankaifaZheShouce/README.md
QianduankaifaZheShouce/__init__.py
QianduankaifaZheShouce/__main__.py
QianduankaifaZheShouce/file.epub
QianduankaifaZheShouce/index.html
QianduankaifaZheShouce/css/__init__.py
QianduankaifaZheShouce/css/annotations.css
QianduankaifaZheShouce/css/main.css
QianduankaifaZheShouce/css/normalize.css
QianduankaifaZheShouce/css/popup.css
QianduankaifaZheShouce/font/__init__.py
QianduankaifaZheShouce/font/fontello.eot
QianduankaifaZheShouce/font/fontello.svg
QianduankaifaZheShouce/font/fontello.ttf
QianduankaifaZheShouce/font/fontello.woff
QianduankaifaZheShouce/img/__init__.py
QianduankaifaZheShouce/img/annotator-glyph-sprite.png
QianduankaifaZheShouce/img/annotator-icon-sprite.png
QianduankaifaZheShouce/img/apple-touch-icon.png
QianduankaifaZheShouce/img/cancelfullscreen.png
QianduankaifaZheShouce/img/close.png
QianduankaifaZheShouce/img/fullscreen.png
QianduankaifaZheShouce/img/loader.gif
QianduankaifaZheShouce/img/menu-icon.png
QianduankaifaZheShouce/img/save.png
QianduankaifaZheShouce/img/saved.png
QianduankaifaZheShouce/img/settings-s.png
QianduankaifaZheShouce/img/settings.png
QianduankaifaZheShouce/img/star.png
QianduankaifaZheShouce/js/__init__.py
QianduankaifaZheShouce/js/epub.js
QianduankaifaZheShouce/js/epub.min.js
QianduankaifaZheShouce/js/epub.min.map
QianduankaifaZheShouce/js/hooks.min.js
QianduankaifaZheShouce/js/hooks.min.map
QianduankaifaZheShouce/js/reader.js
QianduankaifaZheShouce/js/reader.js.map
QianduankaifaZheShouce/js/reader.min.js
QianduankaifaZheShouce/js/reader.min.map
QianduankaifaZheShouce/js/hooks/__init__.py
QianduankaifaZheShouce/js/hooks/extensions/__init__.py
QianduankaifaZheShouce/js/hooks/extensions/highlight.js
QianduankaifaZheShouce/js/libs/__init__.py
QianduankaifaZheShouce/js/libs/jquery.min.js
QianduankaifaZheShouce/js/libs/localforage.min.js
QianduankaifaZheShouce/js/libs/screenfull.js
QianduankaifaZheShouce/js/libs/screenfull.min.js
QianduankaifaZheShouce/js/libs/zip.min.js
qianduankaifa_zhe_shouce-2024.3.2.0.dist-info/METADATA
qianduankaifa_zhe_shouce-2024.3.2.0.dist-info/WHEEL
qianduankaifa_zhe_shouce-2024.3.2.0.dist-info/entry_points.txt
qianduankaifa_zhe_shouce-2024.3.2.0.dist-info/top_level.txt
qianduankaifa_zhe_shouce-2024.3.2.0.dist-info/RECORD
